ftpkg/__init__.py
ftpkg/augmentation/__init__.py
ftpkg/augmentation/dataflow.py
ftpkg/demo/__init__.py
ftpkg/demo/dataset.py
ftpkg/demo/loss.py
ftpkg/demo/model.py
ftpkg/demo/optimizer.py
ftpkg/minetorch/__init__.py
ftpkg/rsna/__init__.py
ftpkg/rsna/dataflow.py
ftpkg/rsna/dataset.py
ftpkg/rsna/loss.py
ftpkg/rsna/model.py
ftpkg/rsna/optimizer.py
ftpkg/ssdd/__init__.py
ftpkg/ssdd/dataflow.py
ftpkg/ssdd/dataset.py
ftpkg/ssdd/loss.py
ftpkg/ssdd/model.py
ftpkg/ssdd/optimizer.py
ftpkg/ssdd/unet.py
featurize_package-0.0.20.dist-info/METADATA
featurize_package-0.0.20.dist-info/WHEEL
featurize_package-0.0.20.dist-info/top_level.txt
featurize_package-0.0.20.dist-info/RECORD
